{"cameraMode":{"drawMode":0,"name":"Shaded","section":"Shading Mode"},"sceneLighting":true,"audioPlay":false,"sceneViewState":{"m_AlwaysRefresh":false,"showFog":true,"showSkybox":true,"showFlares":true,"showImageEffects":true,"showParticleSystems":true,"showVisualEffectGraphs":true,"m_FxEnabled":true},"in2DMode":false,"pivot":{"x":-0.26858121156692507,"y":2.06770920753479,"z":0.15447407960891725},"rotation":{"x":0.06081338971853256,"y":0.6968990564346314,"z":0.05951257050037384,"w":-0.7121187448501587},"size":2.299024820327759,"orthographic":false}